diffpy/__init__.py
diffpy/srxplanar/__init__.py
diffpy/srxplanar/calculate.py
diffpy/srxplanar/loadimage.py
diffpy/srxplanar/mask.py
diffpy/srxplanar/saveresults.py
diffpy/srxplanar/selfcalibrate.py
diffpy/srxplanar/srxplanar.py
diffpy/srxplanar/srxplanar_app.py
diffpy/srxplanar/srxplanarconfig.py
diffpy/srxplanar/tifffile.py
diffpy/srxplanar/version.py
diffpy_srxplanar-1.0.1.dist-info/licenses/AUTHORS.rst
diffpy_srxplanar-1.0.1.dist-info/licenses/LICENSE.rst
diffpy_srxplanar-1.0.1.dist-info/METADATA
diffpy_srxplanar-1.0.1.dist-info/WHEEL
diffpy_srxplanar-1.0.1.dist-info/entry_points.txt
diffpy_srxplanar-1.0.1.dist-info/top_level.txt
diffpy_srxplanar-1.0.1.dist-info/RECORD
